easymsgbox/__init__.py
msg_box/__init__.py
pymsgbox/__init__.py
sysmsgbox/__init__.py
easymsgbox-0.1.0.dist-info/METADATA
easymsgbox-0.1.0.dist-info/WHEEL
easymsgbox-0.1.0.dist-info/top_level.txt
easymsgbox-0.1.0.dist-info/RECORD
