Metadata-Version: 2.1
Name: easymsgbox
Version: 0.1.0
Summary: Easy message box in Python
Home-page: https://easymsgbox.readthedocs.io/
Author: Andrey
Author-email: andrey.gurtov@gmail.com
License: MIT
Classifier: Intended Audience :: Developers
Classifier: License :: OSI Approved :: MIT License
Classifier: Programming Language :: Python
Classifier: Programming Language :: Python :: 3
Classifier: Programming Language :: Python :: 3.6
Classifier: Programming Language :: Python :: 3.7
Classifier: Programming Language :: Python :: 3.8
Classifier: Programming Language :: Python :: 3.9
Classifier: Operating System :: OS Independent
